calculator_mgaidy/__init__.py
calculator_mgaidy/calculator.py
calculator_mgaidy-0.0.7.dist-info/LICENSE
calculator_mgaidy-0.0.7.dist-info/METADATA
calculator_mgaidy-0.0.7.dist-info/WHEEL
calculator_mgaidy-0.0.7.dist-info/top_level.txt
calculator_mgaidy-0.0.7.dist-info/RECORD
